aws_pinpoint_campaign_builder/__init__.py
aws_pinpoint_campaign_builder/pinpoint_campaign_builder.py
aws_pinpoint_campaign_builder/testing.py
aws_pinpoint_campaign_builder/channel/__init__.py
aws_pinpoint_campaign_builder/channel/channel.py
aws_pinpoint_campaign_builder/email_channel/__init__.py
aws_pinpoint_campaign_builder/email_channel/email_channel.py
aws_pinpoint_campaign_builder/s3_utility/__init__.py
aws_pinpoint_campaign_builder/s3_utility/s3_utility.py
aws_pinpoint_campaign_builder/sms_channel/__init__.py
aws_pinpoint_campaign_builder/sms_channel/sms_channel.py
aws_pinpoint_campaign_builder-0.1.dist-info/LICENSE
aws_pinpoint_campaign_builder-0.1.dist-info/METADATA
aws_pinpoint_campaign_builder-0.1.dist-info/WHEEL
aws_pinpoint_campaign_builder-0.1.dist-info/top_level.txt
aws_pinpoint_campaign_builder-0.1.dist-info/RECORD
